README.md
pyproject.toml
scripts/pre_build.py
src/orangutan/__init__.py
src/orangutan/client/__init__.py
src/orangutan/client/client_generation.py
src/orangutan/client/compliance.py
src/orangutan/client/security.py
src/orangutan/exploration/__init__.py
src/orangutan/exploration/openapi_generation.py
src/orangutan/exploration/specification.py
src/orangutan/exploration/traffic_analysis.py
src/orangutan/interaction/__init__.py
src/orangutan/interaction/data_validation.py
src/orangutan/interaction/error_handling.py
src/orangutan/interaction/rate_limiting.py
src/orangutan/interaction/requests.py
src/orangutan/interaction/schemata.py
src/orangutan/interaction/task_queue/__init__.py
src/orangutan/interaction/task_queue/base.py
src/orangutan/interaction/task_queue/basic_backend.py
src/orangutan/interaction/task_queue/celery_backend.py
src/orangutan/models/__init__.py
src/orangutan/models/api_error.py
src/orangutan/models/api_request.py
src/orangutan/models/http_error.py
src/orangutan/models/http_message.py
src/orangutan/models/log_message.py
src/orangutan/monitoring/__init__.py
src/orangutan/monitoring/adaptation.py
src/orangutan/monitoring/logging.py
src/orangutan/utils/__init__.py
src/orangutan/utils/constants.py
src/orangutan/utils/helpers.py
orangutan-0.0.2.dist-info/METADATA
orangutan-0.0.2.dist-info/WHEEL
orangutan-0.0.2.dist-info/RECORD
